{
  "meta": {
    "title": "IT projects (authoring)",
    "note": "Стоимость (cost) оплачивается жетонами задач того же цвета: orange, pink, purple, cyan (голубой). effect и effectDescription пока null — заполнять по ходу.",
    "fields": [
      "id",
      "color",
      "shape",
      "name",
      "cost",
      "effect",
      "effectDescription",
      "victoryPoints",
      "playerCount",
      "imageUrl"
    ]
  },
  "projects": [
    {
      "id": 1,
      "color": null,
      "shape": null,
      "name": null,
      "cost": null,
      "effect": null,
      "effectDescription": null,
      "victoryPoints": null,
      "playerCount": null,
      "imageUrl": null
    },
    {
      "id": 2,
      "color": null,
      "shape": null,
      "name": null,
      "cost": null,
      "effect": null,
      "effectDescription": null,
      "victoryPoints": null,
      "playerCount": null,
      "imageUrl": null
    },
    {
      "id": 3,
      "color": null,
      "shape": null,
      "name": null,
      "cost": null,
      "effect": null,
      "effectDescription": null,
      "victoryPoints": null,
      "playerCount": null,
      "imageUrl": null
    },
    {
      "id": 4,
      "color": null,
      "shape": null,
      "name": null,
      "cost": null,
      "effect": null,
      "effectDescription": null,
      "victoryPoints": null,
      "playerCount": null,
      "imageUrl": null
    },
    {
      "id": 5,
      "color": null,
      "shape": null,
      "name": null,
      "cost": null,
      "effect": null,
      "effectDescription": null,
      "victoryPoints": null,
      "playerCount": null,
      "imageUrl": null
    },
    {
      "id": 6,
      "color": null,
      "shape": null,
      "name": null,
      "cost": null,
      "effect": null,
      "effectDescription": null,
      "victoryPoints": null,
      "playerCount": null,
      "imageUrl": null
    },
    {
      "id": 7,
      "color": null,
      "shape": null,
      "name": null,
      "cost": null,
      "effect": null,
      "effectDescription": null,
      "victoryPoints": null,
      "playerCount": null,
      "imageUrl": null
    },
    {
      "id": 8,
      "color": null,
      "shape": null,
      "name": null,
      "cost": null,
      "effect": null,
      "effectDescription": null,
      "victoryPoints": null,
      "playerCount": null,
      "imageUrl": null
    },
    {
      "id": 9,
      "color": null,
      "shape": null,
      "name": null,
      "cost": null,
      "effect": null,
      "effectDescription": null,
      "victoryPoints": null,
      "playerCount": null,
      "imageUrl": null
    },
    {
      "id": 10,
      "color": null,
      "shape": null,
      "name": null,
      "cost": null,
      "effect": null,
      "effectDescription": null,
      "victoryPoints": null,
      "playerCount": null,
      "imageUrl": null
    },
    {
      "id": 11,
      "color": null,
      "shape": null,
      "name": null,
      "cost": null,
      "effect": null,
      "effectDescription": null,
      "victoryPoints": null,
      "playerCount": null,
      "imageUrl": null
    },
    {
      "id": 12,
      "color": null,
      "shape": null,
      "name": null,
      "cost": null,
      "effect": null,
      "effectDescription": null,
      "victoryPoints": null,
      "playerCount": null,
      "imageUrl": null
    },
    {
      "id": 13,
      "color": null,
      "shape": null,
      "name": null,
      "cost": null,
      "effect": null,
      "effectDescription": null,
      "victoryPoints": null,
      "playerCount": null,
      "imageUrl": null
    },
    {
      "id": 14,
      "color": null,
      "shape": null,
      "name": null,
      "cost": null,
      "effect": null,
      "effectDescription": null,
      "victoryPoints": null,
      "playerCount": null,
      "imageUrl": null
    },
    {
      "id": 15,
      "color": null,
      "shape": null,
      "name": null,
      "cost": null,
      "effect": null,
      "effectDescription": null,
      "victoryPoints": null,
      "playerCount": null,
      "imageUrl": null
    },
    {
      "id": 16,
      "color": null,
      "shape": null,
      "name": null,
      "cost": null,
      "effect": null,
      "effectDescription": null,
      "victoryPoints": null,
      "playerCount": null,
      "imageUrl": null
    },
    {
      "id": 17,
      "color": null,
      "shape": null,
      "name": null,
      "cost": null,
      "effect": null,
      "effectDescription": null,
      "victoryPoints": null,
      "playerCount": null,
      "imageUrl": null
    },
    {
      "id": 18,
      "color": null,
      "shape": null,
      "name": null,
      "cost": null,
      "effect": null,
      "effectDescription": null,
      "victoryPoints": null,
      "playerCount": null,
      "imageUrl": null
    },
    {
      "id": 19,
      "color": null,
      "shape": null,
      "name": null,
      "cost": null,
      "effect": null,
      "effectDescription": null,
      "victoryPoints": null,
      "playerCount": null,
      "imageUrl": null
    },
    {
      "id": 20,
      "color": null,
      "shape": null,
      "name": null,
      "cost": null,
      "effect": null,
      "effectDescription": null,
      "victoryPoints": null,
      "playerCount": null,
      "imageUrl": null
    },
    {
      "id": 21,
      "color": null,
      "shape": null,
      "name": null,
      "cost": null,
      "effect": null,
      "effectDescription": null,
      "victoryPoints": null,
      "playerCount": null,
      "imageUrl": null
    },
    {
      "id": 22,
      "color": null,
      "shape": null,
      "name": null,
      "cost": null,
      "effect": null,
      "effectDescription": null,
      "victoryPoints": null,
      "playerCount": null,
      "imageUrl": null
    },
    {
      "id": 23,
      "color": null,
      "shape": null,
      "name": null,
      "cost": null,
      "effect": null,
      "effectDescription": null,
      "victoryPoints": null,
      "playerCount": null,
      "imageUrl": null
    },
    {
      "id": 24,
      "color": null,
      "shape": null,
      "name": null,
      "cost": null,
      "effect": null,
      "effectDescription": null,
      "victoryPoints": null,
      "playerCount": null,
      "imageUrl": null
    },
    {
      "id": 25,
      "color": null,
      "shape": null,
      "name": null,
      "cost": null,
      "effect": null,
      "effectDescription": null,
      "victoryPoints": null,
      "playerCount": null,
      "imageUrl": null
    },
    {
      "id": 26,
      "color": null,
      "shape": null,
      "name": null,
      "cost": null,
      "effect": null,
      "effectDescription": null,
      "victoryPoints": null,
      "playerCount": null,
      "imageUrl": null
    },
    {
      "id": 27,
      "color": null,
      "shape": null,
      "name": null,
      "cost": null,
      "effect": null,
      "effectDescription": null,
      "victoryPoints": null,
      "playerCount": null,
      "imageUrl": null
    },
    {
      "id": 28,
      "color": null,
      "shape": null,
      "name": null,
      "cost": null,
      "effect": null,
      "effectDescription": null,
      "victoryPoints": null,
      "playerCount": null,
      "imageUrl": null
    },
    {
      "id": 29,
      "color": null,
      "shape": null,
      "name": null,
      "cost": null,
      "effect": null,
      "effectDescription": null,
      "victoryPoints": null,
      "playerCount": null,
      "imageUrl": null
    },
    {
      "id": 30,
      "color": null,
      "shape": null,
      "name": null,
      "cost": null,
      "effect": null,
      "effectDescription": null,
      "victoryPoints": null,
      "playerCount": null,
      "imageUrl": null
    },
    {
      "id": 31,
      "color": null,
      "shape": null,
      "name": null,
      "cost": null,
      "effect": null,
      "effectDescription": null,
      "victoryPoints": null,
      "playerCount": null,
      "imageUrl": null
    },
    {
      "id": 32,
      "color": null,
      "shape": null,
      "name": null,
      "cost": null,
      "effect": null,
      "effectDescription": null,
      "victoryPoints": null,
      "playerCount": null,
      "imageUrl": null
    },
    {
      "id": 33,
      "color": null,
      "shape": null,
      "name": null,
      "cost": null,
      "effect": null,
      "effectDescription": null,
      "victoryPoints": null,
      "playerCount": null,
      "imageUrl": null
    },
    {
      "id": 34,
      "color": null,
      "shape": null,
      "name": null,
      "cost": null,
      "effect": null,
      "effectDescription": null,
      "victoryPoints": null,
      "playerCount": null,
      "imageUrl": null
    },
    {
      "id": 35,
      "color": null,
      "shape": null,
      "name": null,
      "cost": null,
      "effect": null,
      "effectDescription": null,
      "victoryPoints": null,
      "playerCount": null,
      "imageUrl": null
    },
    {
      "id": 36,
      "color": null,
      "shape": null,
      "name": null,
      "cost": null,
      "effect": null,
      "effectDescription": null,
      "victoryPoints": null,
      "playerCount": null,
      "imageUrl": null
    },
    {
      "id": 37,
      "color": null,
      "shape": null,
      "name": null,
      "cost": null,
      "effect": null,
      "effectDescription": null,
      "victoryPoints": null,
      "playerCount": null,
      "imageUrl": null
    },
    {
      "id": 38,
      "color": null,
      "shape": null,
      "name": null,
      "cost": null,
      "effect": null,
      "effectDescription": null,
      "victoryPoints": null,
      "playerCount": null,
      "imageUrl": null
    },
    {
      "id": 39,
      "color": null,
      "shape": null,
      "name": null,
      "cost": null,
      "effect": null,
      "effectDescription": null,
      "victoryPoints": null,
      "playerCount": null,
      "imageUrl": null
    },
    {
      "id": 40,
      "color": null,
      "shape": null,
      "name": null,
      "cost": null,
      "effect": null,
      "effectDescription": null,
      "victoryPoints": null,
      "playerCount": null,
      "imageUrl": null
    },
    {
      "id": 41,
      "color": null,
      "shape": null,
      "name": null,
      "cost": null,
      "effect": null,
      "effectDescription": null,
      "victoryPoints": null,
      "playerCount": null,
      "imageUrl": null
    },
    {
      "id": 42,
      "color": null,
      "shape": null,
      "name": null,
      "cost": null,
      "effect": null,
      "effectDescription": null,
      "victoryPoints": null,
      "playerCount": null,
      "imageUrl": null
    },
    {
      "id": 43,
      "color": null,
      "shape": null,
      "name": null,
      "cost": null,
      "effect": null,
      "effectDescription": null,
      "victoryPoints": null,
      "playerCount": null,
      "imageUrl": null
    },
    {
      "id": 44,
      "color": null,
      "shape": null,
      "name": null,
      "cost": null,
      "effect": null,
      "effectDescription": null,
      "victoryPoints": null,
      "playerCount": null,
      "imageUrl": null
    },
    {
      "id": 45,
      "color": null,
      "shape": null,
      "name": null,
      "cost": null,
      "effect": null,
      "effectDescription": null,
      "victoryPoints": null,
      "playerCount": null,
      "imageUrl": null
    },
    {
      "id": 46,
      "color": null,
      "shape": null,
      "name": null,
      "cost": null,
      "effect": null,
      "effectDescription": null,
      "victoryPoints": null,
      "playerCount": null,
      "imageUrl": null
    },
    {
      "id": 47,
      "color": null,
      "shape": null,
      "name": null,
      "cost": null,
      "effect": null,
      "effectDescription": null,
      "victoryPoints": null,
      "playerCount": null,
      "imageUrl": null
    },
    {
      "id": 48,
      "color": null,
      "shape": null,
      "name": null,
      "cost": null,
      "effect": null,
      "effectDescription": null,
      "victoryPoints": null,
      "playerCount": null,
      "imageUrl": null
    },
    {
      "id": 49,
      "color": null,
      "shape": null,
      "name": null,
      "cost": null,
      "effect": null,
      "effectDescription": null,
      "victoryPoints": null,
      "playerCount": null,
      "imageUrl": null
    },
    {
      "id": 50,
      "color": null,
      "shape": null,
      "name": null,
      "cost": null,
      "effect": null,
      "effectDescription": null,
      "victoryPoints": null,
      "playerCount": null,
      "imageUrl": null
    },
    {
      "id": 51,
      "color": null,
      "shape": null,
      "name": null,
      "cost": null,
      "effect": null,
      "effectDescription": null,
      "victoryPoints": null,
      "playerCount": null,
      "imageUrl": null
    },
    {
      "id": 52,
      "color": null,
      "shape": null,
      "name": null,
      "cost": null,
      "effect": null,
      "effectDescription": null,
      "victoryPoints": null,
      "playerCount": null,
      "imageUrl": null
    },
    {
      "id": 53,
      "color": null,
      "shape": null,
      "name": null,
      "cost": null,
      "effect": null,
      "effectDescription": null,
      "victoryPoints": null,
      "playerCount": null,
      "imageUrl": null
    },
    {
      "id": 54,
      "color": null,
      "shape": null,
      "name": null,
      "cost": null,
      "effect": null,
      "effectDescription": null,
      "victoryPoints": null,
      "playerCount": null,
      "imageUrl": null
    },
    {
      "id": 55,
      "color": null,
      "shape": null,
      "name": null,
      "cost": null,
      "effect": null,
      "effectDescription": null,
      "victoryPoints": null,
      "playerCount": null,
      "imageUrl": null
    },
    {
      "id": 56,
      "color": null,
      "shape": null,
      "name": null,
      "cost": null,
      "effect": null,
      "effectDescription": null,
      "victoryPoints": null,
      "playerCount": null,
      "imageUrl": null
    },
    {
      "id": 57,
      "color": null,
      "shape": null,
      "name": null,
      "cost": null,
      "effect": null,
      "effectDescription": null,
      "victoryPoints": null,
      "playerCount": null,
      "imageUrl": null
    }
  ]
}